.coverage
.flake8
.gitignore
CHANGELOG.md
README.md
pyproject.toml
requirements-dev.txt
requirements.txt
setup.py
.github/dependabot.yml
.github/workflows/docs.yml
.github/workflows/project-actions.yml
.github/workflows/release-please.yml
sample-config/sample.json
sample-config/sample.yml
sample-config/config-json/main.json
sample-config/config-json/pipeline.json
sample-config/config-json/function/function_1.json
sample-config/config-json/function/function_2.json
sample-config/config-mix/basic.yml
sample-config/config-mix/param.yml
sample-config/config-mix/pipeline.json
sample-config/config-mix/function/function1.json
sample-config/config-mix/function/function2.yml
sample-config/config-yml/main.yml
sample-config/config-yml/pipeline.yml
sample-config/config-yml/function/function_1.yml
sample-config/config-yml/function/function_2.yml
src/genconfig/__init__.py
src/genconfig/__main__.py
src/genconfig/base_parser.py
src/genconfig/cli.py
src/genconfig/utils.py
src/genconfig.egg-info/PKG-INFO
src/genconfig.egg-info/SOURCES.txt
src/genconfig.egg-info/dependency_links.txt
src/genconfig.egg-info/entry_points.txt
src/genconfig.egg-info/requires.txt
src/genconfig.egg-info/top_level.txt
src/genconfig/parsers/__init__.py
src/genconfig/parsers/json_parser.py
src/genconfig/parsers/yaml_parser.py
tests/README.md
tests/test_parser.py