Metadata-Version: 2.1
Name: genconfig
Version: 1.3.0
Summary: Manage Json and Yaml config using folder structure
Home-page: https://github.com/lingjie00/genconfig
Author: Ling
Author-email: lingjie@u.nus.edu
License: MIT
Project-URL: Bug Tracker, https://github.com/lingjie00/genconfig/issues
Classifier: Programming Language :: Python :: 3
Classifier: License :: OSI Approved :: MIT License
Classifier: Operating System :: OS Independent
Requires-Python: >=3.8
